{
	"name": "Contact",
	"fields": {
		"contact": {
			"title": "Contact Fields",
			"type": "section",
			"items": {
				"address": "wysiwyg",
				"phone_numer": "text",
				"email_address": "text",
				"hours": {
					"type": "repeater",
					"items": {
						"hours": "text",
						"day": "text"
					}
				}
			}
		},
		"SEO": {
			"title": "SEO",
			"type": "section",
			"items": {
				"keywords": "text",
				"image": "image"
			}
		}
	},
	"wireframe": [
		"section-contact",
		"section-SEO"
	]
}